AUTHORS
CONTRIBUTORS
LICENSE.txt
MANIFEST.in
README.rst
ez_setup.py
setup.py
fabulous/__init__.py
fabulous/_xterm256.c
fabulous/balls.png
fabulous/casts.py
fabulous/color.py
fabulous/compatibility.py
fabulous/debug.py
fabulous/demo.py
fabulous/gotham.py
fabulous/grapefruit.py
fabulous/image.py
fabulous/logs.py
fabulous/prompt.py
fabulous/queries.py
fabulous/rlcomplete.py
fabulous/rotating_cube.py
fabulous/term.py
fabulous/test_transientlogging.py
fabulous/text.py
fabulous/utils.py
fabulous/widget.py
fabulous/xterm256.py
fabulous.egg-info/PKG-INFO
fabulous.egg-info/SOURCES.txt
fabulous.egg-info/dependency_links.txt
fabulous.egg-info/entry_points.txt
fabulous.egg-info/not-zip-safe
fabulous.egg-info/top_level.txt
fabulous/experimental/__init__.py
fabulous/experimental/canvas.py
fabulous/fonts/LICENSE.txt
fabulous/fonts/NotoEmoji-Regular.ttf
fabulous/fonts/NotoSans-Bold.ttf