Metadata-Version: 1.1
Name: fabulous
Version: 0.4.0
Summary: Makes your terminal output totally fabulous
Home-page: https://jart.github.io/fabulous
Author: Justine Tunney
Author-email: jtunney@gmail.com
License: Apache 2.0 / OFL
Download-URL: https://github.com/jart/fabulous/releases/download/0.4.0/fabulous-0.4.0.tar.gz
Platform: UNKNOWN
Classifier: Development Status :: 5 - Production/Stable
Classifier: License :: OSI Approved :: Apache Software License
Classifier: Environment :: Console
Classifier: Intended Audience :: Developers
Classifier: Programming Language :: C
Classifier: Programming Language :: Python
Classifier: Topic :: Utilities
Classifier: Topic :: Artistic Software
Classifier: Topic :: System :: Logging
Classifier: Topic :: Multimedia :: Graphics
